ustcwlt/__init__.py
ustcwlt/account.py
ustcwlt/error.py
ustcwlt/html.py
ustcwlt/url.py
USTCWlt-1.0.1.dist-info/LICENSE
USTCWlt-1.0.1.dist-info/METADATA
USTCWlt-1.0.1.dist-info/WHEEL
USTCWlt-1.0.1.dist-info/top_level.txt
USTCWlt-1.0.1.dist-info/RECORD
