Metadata-Version: 2.1
Name: USTCWlt
Version: 1.0.1
Summary: campus network of USTC
Home-page: https://github.com/littzhch/USTCWlt
Author: littzhch
Author-email: 2371050115@qq.com
License: UNKNOWN
Project-URL: Bug Tracker, https://github.com/littzhch/USTCWlt/issues
Platform: UNKNOWN
Classifier: Programming Language :: Python :: 3
Classifier: License :: OSI Approved :: GNU General Public License v3 (GPLv3)
Classifier: Operating System :: OS Independent
Requires-Python: >=3.6
License-File: LICENSE
